README
setup.py
touchpad/__init__.py
touchpad/touchpad.py
touchpad.egg-info/PKG-INFO
touchpad.egg-info/SOURCES.txt
touchpad.egg-info/dependency_links.txt
touchpad.egg-info/entry_points.txt
touchpad.egg-info/requires.txt
touchpad.egg-info/top_level.txt