Metadata-Version: 1.1
Name: touchpad
Version: 0.1.3
Summary: Toggle touchpad on/off
Home-page: https://github.com/abo-abo/touchpad-toggle
Author: Oleh Krehel
Author-email: ohwoeowho@gmail.com
License: GPLv3+
Keywords: touchpad
Platform: UNKNOWN
Classifier: Development Status :: 3 - Alpha
Classifier: Intended Audience :: End Users/Desktop
Classifier: Environment :: X11 Applications
Classifier: License :: OSI Approved :: GNU General Public License v3 or later (GPLv3+)
Classifier: Programming Language :: Python :: 2
Classifier: Programming Language :: Python :: 2.7
Classifier: Programming Language :: Python :: 3
Classifier: Programming Language :: Python :: 3.3
Classifier: Programming Language :: Python :: 3.4
Classifier: Programming Language :: Python :: 3.5
